batchTranslate/__init__.py
batchTranslate/main.py
batchTranslate-1.5.dist-info/METADATA
batchTranslate-1.5.dist-info/WHEEL
batchTranslate-1.5.dist-info/top_level.txt
batchTranslate-1.5.dist-info/RECORD
