Metadata-Version: 2.1
Name: batchTranslate
Version: 1.5
Summary: The library that lets you translate things a bunch of times
Author: bestCoder1877
Requires: deep_translator
